dllhook/__init__.py
dllhook/__main__.py
dllhook/hooker.py
dllhook/main.py
dllhook/mayhem/.git
dllhook/mayhem/.gitignore
dllhook/mayhem/LICENSE
dllhook/mayhem/Pipfile
dllhook/mayhem/README.md
dllhook/mayhem/REFERENCES.md
dllhook/mayhem/docs/source/conf.py
dllhook/mayhem/docs/source/index.rst
dllhook/mayhem/docs/source/mayhem/index.rst
dllhook/mayhem/docs/source/mayhem/utilities.rst
dllhook/mayhem/docs/source/mayhem/proc/index.rst
dllhook/mayhem/docs/source/mayhem/proc/linux.rst
dllhook/mayhem/docs/source/mayhem/proc/native.rst
dllhook/mayhem/docs/source/mayhem/proc/windows.rst
dllhook/mayhem/examples/cve_2016_3308_bsod.py
dllhook/mayhem/examples/cve_2020_17087_bsod.py
dllhook/mayhem/examples/inject_hook_getclipboarddata.py
dllhook/mayhem/mayhem/__init__.py
dllhook/mayhem/mayhem/utilities.py
dllhook/mayhem/mayhem/__pycache__/__init__.cpython-311.pyc
dllhook/mayhem/mayhem/__pycache__/utilities.cpython-311.pyc
dllhook/mayhem/mayhem/data/README.md
dllhook/mayhem/mayhem/data/windows_syscalls.db
dllhook/mayhem/mayhem/datatypes/__init__.py
dllhook/mayhem/mayhem/datatypes/common.py
dllhook/mayhem/mayhem/datatypes/elf.py
dllhook/mayhem/mayhem/datatypes/windows.py
dllhook/mayhem/mayhem/datatypes/windows_ntstatus.py
dllhook/mayhem/mayhem/datatypes/__pycache__/__init__.cpython-311.pyc
dllhook/mayhem/mayhem/datatypes/__pycache__/common.cpython-311.pyc
dllhook/mayhem/mayhem/datatypes/__pycache__/windows.cpython-311.pyc
dllhook/mayhem/mayhem/datatypes/__pycache__/windows_ntstatus.cpython-311.pyc
dllhook/mayhem/mayhem/exploit/__init__.py
dllhook/mayhem/mayhem/exploit/windows.py
dllhook/mayhem/mayhem/proc/__init__.py
dllhook/mayhem/mayhem/proc/linux.py
dllhook/mayhem/mayhem/proc/native.py
dllhook/mayhem/mayhem/proc/windows.py
dllhook/mayhem/mayhem/proc/__pycache__/__init__.cpython-311.pyc
dllhook/mayhem/mayhem/proc/__pycache__/windows.cpython-311.pyc
dllhook/mayhem/mayhem/windll/__init__.py
dllhook/mayhem/mayhem/windll/bcrypt.py
dllhook/mayhem/mayhem/windll/gdi32.py
dllhook-0.1.2.dist-info/LICENSE
dllhook-0.1.2.dist-info/METADATA
dllhook-0.1.2.dist-info/WHEEL
dllhook-0.1.2.dist-info/top_level.txt
dllhook-0.1.2.dist-info/RECORD
